clock_plot/__init__.py
clock_plot/clock.py
clock_plot-0.2.1.dist-info/LICENSE
clock_plot-0.2.1.dist-info/METADATA
clock_plot-0.2.1.dist-info/WHEEL
clock_plot-0.2.1.dist-info/top_level.txt
clock_plot-0.2.1.dist-info/RECORD
