Metadata-Version: 2.1
Name: clock-plot
Version: 0.2.1
Summary: This package provides a simple way to visualize patterns in timeseries data mapping 24 hours onto a polar plot
Home-page: https://github.com/esc-data-science/clock_plot
Author: Samuel Young
Author-email: samuel.young.work@gmail.com
License: UNKNOWN
Project-URL: Bug Tracker, https://github.com/esc-data-science/clock_plot/issues
Platform: UNKNOWN
Classifier: Programming Language :: Python :: 3
Classifier: License :: OSI Approved :: MIT License
Classifier: Operating System :: OS Independent
Requires-Python: >=3.7
License-File: LICENSE
Requires-Dist: numpy (>=1.20.3)
Requires-Dist: pandas (>=1.3.4)
Requires-Dist: plotly (>=4.0.0)
Requires-Dist: scipy (>=1.7.1)
